cvxstoc/__init__.py
cvxstoc/diagnostics.py
cvxstoc/expectation.py
cvxstoc/prob.py
cvxstoc/random_variable.py
cvxstoc/strings.py
cvxstoc/utils.py
cvxstoc-0.2.2.dist-info/METADATA
cvxstoc-0.2.2.dist-info/WHEEL
cvxstoc-0.2.2.dist-info/top_level.txt
cvxstoc-0.2.2.dist-info/RECORD
